<?xml version="1.0"?>
<VpSizeADD xmlns:xsd="http://www.w3.org/2001/XMLSchema" xmlns:xsi="http://www.w3.org/2001/XMLSchema-instance">
  <folder>VOC2007</folder>
  <filename>C:\Users\Administrator\Desktop\分配-叶明慧儿-400-2018.7.5\HCZ_HFGTNZ_20180621_10248.jpg</filename>
  <segmented>0</segmented>
  <source>
    <database>The VOC2007 Database</database>
    <annotation>PASCAL VOC2007</annotation>
    <image>flickr</image>
    <flickrid>330391518</flickrid>
  </source>
  <owner>
    <flickrid>supershoppertoo</flickrid>
    <name>cnivs</name>
  </owner>
  <size>
    <width>801</width>
    <height>382</height>
    <depth>3</depth>
  </size>
  <object>
    <name>smallelectronicequipmen</name>
    <pose>Unspecified</pose>
    <truncated>0</truncated>
    <difficult>0</difficult>
    <bndbox>
      <xmin>579</xmin>
      <ymin>208</ymin>
      <xmax>640</xmax>
      <ymax>304</ymax>
    </bndbox>
  </object>
  <object>
    <name>glassbottle</name>
    <pose>Unspecified</pose>
    <truncated>0</truncated>
    <difficult>0</difficult>
    <bndbox>
      <xmin>163</xmin>
      <ymin>194</ymin>
      <xmax>202</xmax>
      <ymax>236</ymax>
    </bndbox>
  </object>
  <object>
    <name>glassbottle</name>
    <pose>Unspecified</pose>
    <truncated>0</truncated>
    <difficult>0</difficult>
    <bndbox>
      <xmin>130</xmin>
      <ymin>313</ymin>
      <xmax>167</xmax>
      <ymax>352</ymax>
    </bndbox>
  </object>
  <VpSize>
    <Xmin>115</Xmin>
    <Ymin>167</Ymin>
    <Xmax>299</Xmax>
    <Ymax>351</Ymax>
  </VpSize>
  <VpSize>
    <Xmin>446</Xmin>
    <Ymin>30</Ymin>
    <Xmax>801</Xmax>
    <Ymax>351</Ymax>
  </VpSize>
</VpSizeADD>