<?xml version="1.0"?>
<VpSizeADD xmlns:xsd="http://www.w3.org/2001/XMLSchema" xmlns:xsi="http://www.w3.org/2001/XMLSchema-instance">
  <folder>VOC2007</folder>
  <filename>C:\Users\Administrator\Desktop\分配-叶明慧儿-400-2018.7.5\HCZ_HFGTNZ_20180621_10103.jpg</filename>
  <segmented>0</segmented>
  <source>
    <database>The VOC2007 Database</database>
    <annotation>PASCAL VOC2007</annotation>
    <image>flickr</image>
    <flickrid>330391518</flickrid>
  </source>
  <owner>
    <flickrid>supershoppertoo</flickrid>
    <name>cnivs</name>
  </owner>
  <size>
    <width>801</width>
    <height>574</height>
    <depth>3</depth>
  </size>
  <object>
    <name>smallelectronicequipmen</name>
    <pose>Unspecified</pose>
    <truncated>0</truncated>
    <difficult>0</difficult>
    <bndbox>
      <xmin>494</xmin>
      <ymin>376</ymin>
      <xmax>559</xmax>
      <ymax>465</ymax>
    </bndbox>
  </object>
  <object>
    <name>umbrella</name>
    <pose>Unspecified</pose>
    <truncated>0</truncated>
    <difficult>0</difficult>
    <bndbox>
      <xmin>504</xmin>
      <ymin>376</ymin>
      <xmax>599</xmax>
      <ymax>543</ymax>
    </bndbox>
  </object>
  <object>
    <name>umbrella</name>
    <pose>Unspecified</pose>
    <truncated>0</truncated>
    <difficult>0</difficult>
    <bndbox>
      <xmin>17</xmin>
      <ymin>341</ymin>
      <xmax>148</xmax>
      <ymax>435</ymax>
    </bndbox>
  </object>
  <VpSize>
    <Xmin>302</Xmin>
    <Ymin>287</Ymin>
    <Xmax>594</Xmax>
    <Ymax>544</Ymax>
  </VpSize>
  <VpSize>
    <Xmin>0</Xmin>
    <Ymin>271</Ymin>
    <Xmax>218</Xmax>
    <Ymax>466</Ymax>
  </VpSize>
  <VpSize>
    <Xmin>738</Xmin>
    <Ymin>30</Ymin>
    <Xmax>801</Xmax>
    <Ymax>403</Ymax>
  </VpSize>
</VpSizeADD>