<?xml version="1.0"?>
<VpSizeADD xmlns:xsd="http://www.w3.org/2001/XMLSchema" xmlns:xsi="http://www.w3.org/2001/XMLSchema-instance">
  <folder>VOC2007</folder>
  <filename>C:\Users\Administrator\Desktop\分配-叶明慧儿-400-2018.7.5\HCZ_HFGTNZ_20180621_10206.jpg</filename>
  <segmented>0</segmented>
  <source>
    <database>The VOC2007 Database</database>
    <annotation>PASCAL VOC2007</annotation>
    <image>flickr</image>
    <flickrid>330391518</flickrid>
  </source>
  <owner>
    <flickrid>supershoppertoo</flickrid>
    <name>cnivs</name>
  </owner>
  <size>
    <width>801</width>
    <height>372</height>
    <depth>3</depth>
  </size>
  <object>
    <name>metalcup</name>
    <pose>Unspecified</pose>
    <truncated>0</truncated>
    <difficult>0</difficult>
    <bndbox>
      <xmin>448</xmin>
      <ymin>63</ymin>
      <xmax>576</xmax>
      <ymax>244</ymax>
    </bndbox>
  </object>
  <object>
    <name>glassbottle</name>
    <pose>Unspecified</pose>
    <truncated>0</truncated>
    <difficult>0</difficult>
    <bndbox>
      <xmin>463</xmin>
      <ymin>214</ymin>
      <xmax>585</xmax>
      <ymax>309</ymax>
    </bndbox>
  </object>
  <object>
    <name>umbrella</name>
    <pose>Unspecified</pose>
    <truncated>0</truncated>
    <difficult>0</difficult>
    <bndbox>
      <xmin>115</xmin>
      <ymin>36</ymin>
      <xmax>183</xmax>
      <ymax>196</ymax>
    </bndbox>
  </object>
  <object>
    <name>plasticcup</name>
    <pose>Unspecified</pose>
    <truncated>0</truncated>
    <difficult>0</difficult>
    <bndbox>
      <xmin>1</xmin>
      <ymin>169</ymin>
      <xmax>101</xmax>
      <ymax>226</ymax>
    </bndbox>
  </object>
  <VpSize>
    <Xmin>413</Xmin>
    <Ymin>75</Ymin>
    <Xmax>641</Xmax>
    <Ymax>342</Ymax>
  </VpSize>
  <VpSize>
    <Xmin>0</Xmin>
    <Ymin>30</Ymin>
    <Xmax>279</Xmax>
    <Ymax>220</Ymax>
  </VpSize>
</VpSizeADD>